ns_poet/__init__.py
ns_poet/cli.py
ns_poet/config.py
ns_poet/exceptions.py
ns_poet/generators/__init__.py
ns_poet/generators/base.py
ns_poet/generators/load.py
ns_poet/package.py
ns_poet/package_targets/__init__.py
ns_poet/package_targets/base.py
ns_poet/package_targets/python_package.py
ns_poet/package_targets/requirement.py
ns_poet/processor.py
ns_poet/project.py
ns_poet/requirements.py
ns_poet/util.py
ns_poet-1.0.0.dist-info/entry_points.txt
ns_poet-1.0.0.dist-info/LICENSE.md
ns_poet-1.0.0.dist-info/WHEEL
ns_poet-1.0.0.dist-info/METADATA
ns_poet-1.0.0.dist-info/RECORD
