Metadata-Version: 2.1
Name: ns-poet
Version: 1.0.0
Summary: Autogenerate Poetry package manifests in a monorepo
Home-page: https://github.com/NarrativeScience/ns-poet
License: BSD-3-Clause
Author: Jonathan Drake
Author-email: jdrake@narrativescience.com
Requires-Python: >=3.10,<4.0
Classifier: License :: OSI Approved :: BSD License
Classifier: Programming Language :: Python :: 3
Classifier: Programming Language :: Python :: 3.10
Classifier: Programming Language :: Python :: 3.11
Requires-Dist: astor (>=0.8.1,<1)
Requires-Dist: click (>=8.1.3,<9.0.0)
Requires-Dist: cookiecutter (>=2.1.1,<3.0.0)
Requires-Dist: networkx (>=2.8.7,<3.0.0)
Requires-Dist: setuptools (>=65.5.0,<66.0.0)
Requires-Dist: toml (>=0.10.2,<1)
Project-URL: Repository, https://github.com/NarrativeScience/ns-poet
